UPnP/UPnP.py
UPnP/__init__.py
UPnP-1.3.dist-info/DESCRIPTION.rst
UPnP-1.3.dist-info/METADATA
UPnP-1.3.dist-info/RECORD
UPnP-1.3.dist-info/WHEEL
UPnP-1.3.dist-info/metadata.json
UPnP-1.3.dist-info/top_level.txt
