Metadata-Version: 2.0
Name: UPnP
Version: 1.3
Summary: Forward a Port with UPnP and pure Python script
Home-page: UNKNOWN
Author: NinuX
Author-email: UNKNOWN
License: MIT
Platform: UNKNOWN
Requires-Dist: gevent
Requires-Dist: ipgetter
